ynab_mcp/__init__.py
ynab_mcp/__main__.py
ynab_mcp/exceptions.py
ynab_mcp/server.py
ynab_mcp/validation.py
ynab_mcp/ynab_client.py
ynab_mcp_dgalarza-0.1.1.dist-info/METADATA
ynab_mcp_dgalarza-0.1.1.dist-info/WHEEL
ynab_mcp_dgalarza-0.1.1.dist-info/entry_points.txt
ynab_mcp_dgalarza-0.1.1.dist-info/licenses/LICENSE
ynab_mcp_dgalarza-0.1.1.dist-info/RECORD
