Metadata-Version: 2.4
Name: ynab-mcp-dgalarza
Version: 0.1.1
Summary: MCP server for YNAB (You Need A Budget) integration
Project-URL: Homepage, https://github.com/dgalarza/ynab-mcp-dgalarza
Project-URL: Repository, https://github.com/dgalarza/ynab-mcp-dgalarza
Project-URL: Issues, https://github.com/dgalarza/ynab-mcp-dgalarza/issues
Author-email: Damian Galarza <damian@example.com>
License: MIT
License-File: LICENSE
Keywords: api,budget,mcp,model-context-protocol,ynab
Requires-Python: >=3.10
Requires-Dist: httpx<1.0.0,>=0.27.0
Requires-Dist: mcp<2.0.0,>=1.0.0
Requires-Dist: python-dotenv<2.0.0,>=1.0.0
Requires-Dist: termgraph<1.0.0,>=0.5.3
Requires-Dist: ynab-sdk<1.0.0,>=0.1.0
Provides-Extra: dev
Requires-Dist: pytest-asyncio>=0.23.0; extra == 'dev'
Requires-Dist: pytest>=8.0.0; extra == 'dev'
Requires-Dist: ruff>=0.8.0; extra == 'dev'
